jsonapi_client/__init__.py
jsonapi_client/client.py
jsonapi_client/collection.py
jsonapi_client/decoders.py
jsonapi_client/encoders.py
jsonapi_client/parser.py
jsonapi_client/py.typed
jsonapi_client/query.py
jsonapi_client/resource.py
jsonapi_client/resources_list.py
jsonapi_client/schema.py
jsonapi_client/serializer.py
jsonapi_client/version.py
jsonapi_client_framework-1.0.2.dist-info/licenses/LICENSE
jsonapi_client_framework-1.0.2.dist-info/METADATA
jsonapi_client_framework-1.0.2.dist-info/WHEEL
jsonapi_client_framework-1.0.2.dist-info/top_level.txt
jsonapi_client_framework-1.0.2.dist-info/RECORD
